pyhirte/__init__.py
pyhirte/api.py
pyhirte/ext.py
pyhirte-0.4.0.dist-info/LICENSE
pyhirte-0.4.0.dist-info/METADATA
pyhirte-0.4.0.dist-info/WHEEL
pyhirte-0.4.0.dist-info/top_level.txt
pyhirte-0.4.0.dist-info/zip-safe
pyhirte-0.4.0.dist-info/RECORD
