Metadata-Version: 2.1
Name: pyhirte
Version: 0.4.0
Summary: Python bindings for hirte's D-Bus API
Home-page: https://github.com/containers/hirte/
Author: Hirte developers
License: LGPL-2.0-or-later
Keywords: hirte,python,D-Bus,systemd
Platform: UNKNOWN
Classifier: Programming Language :: Python
Classifier: Programming Language :: Python :: 3
Requires-Python: >=3.9
License-File: LICENSE
Requires-Dist: dasbus
